stackNqueue/DoublyCircularLinkedList.py
stackNqueue/Queue.py
stackNqueue/Stack.py
stackNqueue-0.1.3.dist-info/LICENSE
stackNqueue-0.1.3.dist-info/METADATA
stackNqueue-0.1.3.dist-info/WHEEL
stackNqueue-0.1.3.dist-info/top_level.txt
stackNqueue-0.1.3.dist-info/RECORD
